dosma/__init__.py
dosma/app.py
dosma/cli.py
dosma/defaults.py
dosma/file_constants.py
dosma/core/__init__.py
dosma/core/device.py
dosma/core/fitting.py
dosma/core/med_volume.py
dosma/core/numpy_routines.py
dosma/core/orientation.py
dosma/core/quant_vals.py
dosma/core/registration.py
dosma/core/vis_routines.py
dosma/core/io/__init__.py
dosma/core/io/dicom_io.py
dosma/core/io/format_io.py
dosma/core/io/format_io_utils.py
dosma/core/io/nifti_io.py
dosma/gui/__init__.py
dosma/gui/dosma_gui.py
dosma/gui/gui_errors.py
dosma/gui/im_viewer.py
dosma/gui/ims.py
dosma/gui/preferences_viewer.py
dosma/gui/gui_utils/__init__.py
dosma/gui/gui_utils/console_output.py
dosma/gui/gui_utils/filedialog_reader.py
dosma/gui/gui_utils/gui_utils.py
dosma/models/__init__.py
dosma/models/oaiunet2d.py
dosma/models/seg_model.py
dosma/models/stanford_qdess.py
dosma/models/util.py
dosma/msk/__init__.py
dosma/msk/knee.py
dosma/resources/elastix/params/parameters-affine-interregister.txt
dosma/resources/elastix/params/parameters-affine.txt
dosma/resources/elastix/params/parameters-bspline.txt
dosma/resources/elastix/params/parameters-rigid-interregister.txt
dosma/resources/elastix/params/parameters-rigid.txt
dosma/resources/templates/.preferences.yml
dosma/resources/templates/.preferences_cmd_line_schema.yml
dosma/scan_sequences/__init__.py
dosma/scan_sequences/scan_io.py
dosma/scan_sequences/scans.py
dosma/scan_sequences/mri/__init__.py
dosma/scan_sequences/mri/cones.py
dosma/scan_sequences/mri/cube_quant.py
dosma/scan_sequences/mri/mapss.py
dosma/scan_sequences/mri/qdess.py
dosma/tissues/__init__.py
dosma/tissues/femoral_cartilage.py
dosma/tissues/meniscus.py
dosma/tissues/patellar_cartilage.py
dosma/tissues/tibial_cartilage.py
dosma/tissues/tissue.py
dosma/utils/__init__.py
dosma/utils/cmd_line_utils.py
dosma/utils/collect_env.py
dosma/utils/env.py
dosma/utils/geometry_utils.py
dosma/utils/img_utils.py
dosma/utils/io_utils.py
dosma/utils/logger.py
dosma-0.1.2.dist-info/LICENSE
dosma-0.1.2.dist-info/METADATA
dosma-0.1.2.dist-info/WHEEL
dosma-0.1.2.dist-info/top_level.txt
dosma-0.1.2.dist-info/RECORD
