Metadata-Version: 2.1
Name: dosma
Version: 0.1.2
Summary: An AI-powered open-source medical image analysis toolbox
Home-page: https://github.com/ad12/DOSMA
Author: Arjun Desai
License: GNU
Project-URL: Documentation, https://dosma.readthedocs.io/
Platform: UNKNOWN
Classifier: Programming Language :: Python :: 3
Classifier: License :: OSI Approved :: GNU General Public License v3 (GPLv3)
Classifier: Operating System :: OS Independent
Requires-Python: >=3.6
Requires-Dist: matplotlib
Requires-Dist: numpy
Requires-Dist: h5py
Requires-Dist: natsort
Requires-Dist: nested-lookup
Requires-Dist: nibabel
Requires-Dist: nipype
Requires-Dist: packaging
Requires-Dist: pandas
Requires-Dist: pydicom (>=1.6.0)
Requires-Dist: scikit-image
Requires-Dist: scipy
Requires-Dist: seaborn
Requires-Dist: openpyxl
Requires-Dist: Pmw
Requires-Dist: PyYAML
Requires-Dist: tabulate
Requires-Dist: termcolor
Requires-Dist: tqdm (>=4.42.0)
Provides-Extra: ai
Requires-Dist: tensorflow (<=2.4.1) ; extra == 'ai'
Requires-Dist: keras (<=2.4.3) ; extra == 'ai'
Provides-Extra: dev
Requires-Dist: coverage ; extra == 'dev'
Requires-Dist: flake8 ; extra == 'dev'
Requires-Dist: flake8-bugbear ; extra == 'dev'
Requires-Dist: flake8-comprehensions ; extra == 'dev'
Requires-Dist: isort ; extra == 'dev'
Requires-Dist: black (==21.4b2) ; extra == 'dev'
Requires-Dist: click (==8.0.2) ; extra == 'dev'
Requires-Dist: simpleitk ; extra == 'dev'
Requires-Dist: sphinx ; extra == 'dev'
Requires-Dist: sphinxcontrib.bibtex ; extra == 'dev'
Requires-Dist: m2r2 ; extra == 'dev'
Requires-Dist: tensorflow (<=2.4.1) ; extra == 'dev'
Requires-Dist: keras (<=2.4.3) ; extra == 'dev'
Requires-Dist: sigpy ; extra == 'dev'
Provides-Extra: docs
Requires-Dist: mistune (<2.0.0,>=0.8.1) ; extra == 'docs'
Requires-Dist: sphinx ; extra == 'docs'
Requires-Dist: sphinxcontrib.bibtex ; extra == 'docs'
Requires-Dist: m2r2 ; extra == 'docs'
